authbox_learn/__init__.py
authbox_learn/_version.py
authbox_learn/main.py
authbox_learn-1.0.0.dist-info/licenses/LICENSE
authbox_learn-1.0.0.dist-info/METADATA
authbox_learn-1.0.0.dist-info/WHEEL
authbox_learn-1.0.0.dist-info/entry_points.txt
authbox_learn-1.0.0.dist-info/top_level.txt
authbox_learn-1.0.0.dist-info/RECORD
