Metadata-Version: 2.4
Name: authbox-learn
Version: 1.0.0
Summary: For learn how to create library
Home-page: https://github.com/PROJECT-OUTBOX/authbox_learn.git
Author-email: suratiwan03@gmail.com
Keywords: learn,library,django
Classifier: License :: OSI Approved :: BSD License
Classifier: Intended Audience :: Developers
Classifier: Programming Language :: Python :: 3 :: Only
License-File: LICENSE
Requires-Dist: incremental
Dynamic: author-email
Dynamic: classifier
Dynamic: description
Dynamic: description-content-type
Dynamic: home-page
Dynamic: keywords
Dynamic: license-file
Dynamic: requires-dist
Dynamic: summary
